staircase/__init__.py
staircase/decorators.py
staircase/logger.py
staircase/printer.py
staircase/staircase_example.py
staircase/test.py
staircase/version.py
test/__init__.py
test/test_logger.py
staircase_test-0.0.5.dist-info/METADATA
staircase_test-0.0.5.dist-info/WHEEL
staircase_test-0.0.5.dist-info/top_level.txt
staircase_test-0.0.5.dist-info/RECORD
